{
  "type": "STONE",
  "name": "granite",
  "parent": "default_stone",
  "container": {
    "type": "HOST",
    "id": "minecraft:granite"
  },
  "properties": {
    "attributes": [
      {
        "id": "default_stone_rarity",
        "type": "RARITY",
        "order": "COMPOSITE",
        "operation": "ADDITION",
        "value": 12
      },
      {
        "id": "default_stone_durability",
        "type": "DURABILITY",
        "order": "COMPOSITE",
        "operation": "ADDITION",
        "value": 120.0
      },
      {
        "id": "default_stone_attack_damage",
        "type": "ATTACK_DAMAGE",
        "order": "COMPOSITE",
        "operation": "ADDITION",
        "value": 2.7
      },
      {
        "id": "default_stone_mining_speed",
        "type": "MINING_SPEED",
        "order": "COMPOSITE",
        "operation": "ADDITION",
        "value": 3.8
      }
    ]
  },
  "palette": {
    "name": "granite"
  }
}