{
  "schemaVersion": 1,
  "id": "forgero-common",
  "version": "${version}",
  "name": "Forgero common library",
  "description": "Common Minecraft dependency library for Forgero modules.",
  "authors": [
    "Sigmund Granaas Sandring"
  ],
  "contributors": [
    "Aulluna",
    "Rad233",
    "identithree",
    "macaroni0423",
    "Steveplays28"
  ],
  "contact": {
    "homepage": "https://sigmundgranaas.com",
    "sources": "https://github.com/sigmundgranaas/forgero",
    "issues": "https://github.com/sigmundgranaas/forgero/issues"
  },
  "license": "MIT",
  "icon": "assets/forgero/icon.png",
  "environment": "*",
  "accessWidener": "minecraft-common.accesswidener",
  "entrypoints": {
  },
  "mixins": [
    "common.mixins.json"
  ],
  "depends": {
    "minecraft": "1.20.3",
    "java": ">=17"
  },
  "custom": {
    "forgeroResource": true,
    "modmenu": {
      "links": {
        "modmenu.discord": "https://discord.gg/v6sDsftE9N"
      },
      "badges": [
        "library"
      ],
      "parent": {
        "id": "forgero",
        "name": "Forgero",
        "description": "Equipment crafting expansion mod for Fabric!",
        "icon": "assets/forgero/icon.png"
      }
    }
  }
}
