{
  "type": "STONE",
  "name": "stone_base",
  "resource_type": "ABSTRACT",
  "properties": {
    "grouped_attributes": [
      {
        "context": "COMPOSITE",
        "order": "BASE",
        "operation": "ADDITION",
        "attributes": [
          {
            "id": "stone-attack_speed-composite",
            "type": "ATTACK_SPEED",
            "value": 2
          },
          {
            "id": "stone-attack_damage-composite",
            "type": "ATTACK_DAMAGE",
            "value": 3
          },
          {
            "id": "stone-mining-speed-composite",
            "type": "MINING_SPEED",
            "value": 4
          },
          {
            "id": "stone-mining-level-composite",
            "type": "MINING_LEVEL",
            "value": 1
          },
          {
            "id": "stone-durability-composite",
            "type": "DURABILITY",
            "value": 120
          },
          {
            "id": "stone-rarity-composite",
            "type": "RARITY",
            "value": 20
          },
          {
            "id": "stone-weight-composite",
            "type": "WEIGHT",
            "value": 30
          },
          {
            "id": "stone-armor-composite",
            "type": "ARMOR",
            "value": 3
          }
        ]
      },
      {
        "context": "UPGRADE",
        "attributes": [
          {
            "id": "stone-rarity-upgrade",
            "type": "RARITY",
            "order": "BASE",
            "operation": "ADDITION",
            "category": "ALL",
            "value": 10
          },
          {
            "id": "stone-weight-upgrade",
            "type": "WEIGHT",
            "order": "BASE",
            "operation": "ADDITION",
            "category": "ALL",
            "value": 15
          },
          {
            "id": "stone-attack_speed-offensive-upgrade",
            "type": "ATTACK_SPEED",
            "operation": "ADDITION",
            "category": "OFFENSIVE",
            "value": 0
          },
          {
            "id": "stone-attack_damage-offensive-upgrade",
            "type": "ATTACK_DAMAGE",
            "operation": "ADDITION",
            "category": "OFFENSIVE",
            "value": 1.5
          },
          {
            "id": "stone-mining_speed-offensive-upgrade",
            "type": "MINING_SPEED",
            "operation": "ADDITION",
            "category": "OFFENSIVE",
            "value": 2
          },
          {
            "id": "stone-mining_level-offensive-upgrade",
            "type": "MINING_LEVEL",
            "operation": "ADDITION",
            "category": "OFFENSIVE",
            "value": 0
          },
          {
            "id": "stone-durability-offensive-upgrade",
            "type": "DURABILITY",
            "operation": "ADDITION",
            "category": "OFFENSIVE",
            "value": 60
          },
          {
            "id": "stone-attack_speed-utility-upgrade",
            "type": "ATTACK_SPEED",
            "operation": "ADDITION",
            "category": "UTILITY",
            "value": 0
          },
          {
            "id": "stone-attack_damage-utility-upgrade",
            "type": "ATTACK_DAMAGE",
            "operation": "ADDITION",
            "category": "UTILITY",
            "value": 0
          },
          {
            "id": "stone-mining_speed-utility-upgrade",
            "type": "MINING_SPEED",
            "operation": "ADDITION",
            "category": "UTILITY",
            "value": 0
          },
          {
            "id": "stone-mining_level-utility-upgrade",
            "type": "MINING_LEVEL",
            "operation": "ADDITION",
            "category": "UTILITY",
            "value": 0
          },
          {
            "id": "stone-durability-utility-upgrade",
            "type": "DURABILITY",
            "operation": "ADDITION",
            "category": "UTILITY",
            "value": 60
          }
        ]
      }
    ]
  }
}
