{
  "type": "SPEAR",
  "name": "spear",
  "resource_type": "CONSTRUCT_TEMPLATE",
  "container": {
    "type": "CREATE",
    "id": "this"
  },
  "construct": {
    "type": "SPEAR",
    "target": "CREATE",
    "recipes": [
      {
        "crafting_type": "STATE_CRAFTING_RECIPE",
        "ingredients": [
          {
            "unique": true,
            "type": "SPEAR_HEAD"
          },
          {
            "type": "HANDLE"
          }
        ]
      }
    ],
    "components": [
      {
        "type": "SPEAR_HEAD"
      },
      {
        "type": "HANDLE"
      }
    ],
    "slots": [
    ]
  },
  "model": {
    "type": "COMPOSITE"
  }
}
