{
  "type": "SWORD_BLADE_SCHEMATIC",
  "name": "refined_sword_blade-schematic",
  "parent": "sword_blade_base",
  "container": {
    "type": "CREATE",
    "id": "this"
  },
  "construct": {
    "type": "SWORD_BLADE",
    "target": "CREATE",
    "recipes": [
      {
        "crafting_type": "SCHEMATIC_PART_CRAFTING",
        "ingredients": [
          {
            "id": "this"
          },
          {
            "type": "TOOL_MATERIAL",
            "unique": true,
            "amount": 3
          }
        ]
      }
    ],
    "components": [
      {
        "id": "this"
      },
      {
        "type": "TOOL_MATERIAL",
        "unique": true
      }
    ],
    "slots": [
      {
        "upgrade_type": "SMITHING",
        "category": [
          "OFFENSIVE"
        ],
        "description": "sword_tip",
        "type": "TOOL_MATERIAL",
        "tier": 1
      },
      {
        "upgrade_type": "SMITHING",
        "category": [
          "OFFENSIVE"
        ],
        "description": "trinket",
        "type": "TRINKET",
        "tier": 1
      }
    ],
    "models": [
      {}
    ]
  },
  "properties": {
    "attributes": [
      {
        "id": "schematic-rarity-local",
        "type": "RARITY",
        "order": "BASE",
        "operation": "ADDITION",
        "category": "LOCAL",
        "value": 50
      },
      {
        "id": "schematic-rarity-composite",
        "type": "RARITY",
        "order": "COMPOSITE",
        "operation": "MULTIPLICATION",
        "value": 1.3
      },
      {
        "type": "DURABILITY",
        "order": "COMPOSITE",
        "operation": "MULTIPLICATION",
        "value": 1.3
      },
      {
        "type": "ATTACK_DAMAGE",
        "order": "COMPOSITE",
        "operation": "MULTIPLICATION",
        "value": 1.3
      },
      {
        "type": "ATTACK_SPEED",
        "order": "COMPOSITE",
        "operation": "ADDITION",
        "value": 1.3
      },
      {
        "type": "ATTACK_SPEED",
        "order": "COMPOSITE",
        "operation": "ADDITION",
        "value": -3.0
      },
      {
        "type": "WEIGHT",
        "order": "COMPOSITE",
        "operation": "MULTIPLICATION",
        "value": 1
      }
    ]
  },
  "custom_data": {
    "ingredient_count": {
      "value": 3,
      "context": "LOCAL"
    }
  }
}
