{
  "type": "WOOD",
  "name": "jungle",
  "parent": "wood",
  "container": {
    "type": "HOST",
    "id": "minecraft:jungle_planks"
  },
  "properties": {
    "attributes": [
      {
        "id": "wood-rarity-composite-base",
        "type": "RARITY",
        "order": "COMPOSITE",
        "operation": "ADDITION",
        "value": 9
      },
      {
        "type": "MINING_SPEED",
        "order": "BASE",
        "category": "OFFENSIVE",
        "operation": "ADDITION",
        "value": -0.1
      },
      {
        "type": "ATTACK_DAMAGE",
        "order": "BASE",
        "category": "OFFENSIVE",
        "operation": "ADDITION",
        "value": -0.1
      },
      {
        "type": "ATTACK_SPEED",
        "order": "BASE",
        "category": "UTILITY",
        "operation": "ADDITION",
        "value": -0.1
      },
      {
        "type": "DURABILITY",
        "order": "BASE",
        "category": "UTILITY",
        "operation": "MULTIPLICATION",
        "value": 1.2
      },
      {
        "id": "wood-durability-composite-base",
        "type": "DURABILITY",
        "order": "COMPOSITE",
        "operation": "ADDITION",
        "category": "ALL",
        "value": 60.0
      }
    ],
    "passive": [],
    "active": []
  },
  "palette": {
    "name": "jungle"
  }
}