{
  "type": "STONE",
  "name": "calcite",
  "parent": "default_stone",
  "container": {
    "type": "HOST",
    "id": "minecraft:calcite"
  },
  "properties": {
    "attributes": [
      {
        "id": "stone-rarity-composite",
        "type": "RARITY",
        "context": "COMPOSITE",
        "operation": "ADDITION",
        "value": 18
      },
      {
        "id": "stone-mining-speed-composite",
        "type": "MINING_SPEED",
        "context": "COMPOSITE",
        "operation": "ADDITION",
        "value": 4
      },
      {
        "id": "stone-durability-composite",
        "type": "DURABILITY",
        "context": "COMPOSITE",
        "operation": "ADDITION",
        "value": 180.0
      }
    ]
  },
  "palette": {
    "name": "calcite"
  }
}
