{
  "type": "HANDLE_SCHEMATIC",
  "name": "reinforced_handle-schematic",
  "container": {
    "type": "CREATE",
    "id": "this"
  },
  "construct": {
    "type": "HANDLE",
    "target": "CREATE",
    "recipe": {
    },
    "components": [
      {
        "id": "this"
      },
      {
        "type": "TOOL_MATERIAL",
        "unique": true
      }
    ],
    "slots": [
      {
        "upgrade_type": "SMITHING",
        "description": "grip",
        "category": [
          "OFFENSIVE"
        ],
        "type": "MATERIAL",
        "tier": 1
      },
      {
        "upgrade_type": "SMITHING",
        "description": "pummel",
        "category": [
          "OFFENSIVE"
        ],
        "type": "PUMMEL",
        "tier": 1
      }
    ],
    "models": [
      {}
    ]
  },
  "properties": {
    "attributes": [
      {
        "type": "RARITY",
        "order": "BASE",
        "operation": "ADDITION",
        "value": 30
      }
    ]
  },
  "model": {
    "type": "LAYERED",
    "id": "this"
  }
}