{
  "type": "PICKAXE_HEAD_SCHEMATIC",
  "name": "lightweight_pickaxe_head-schematic",
  "parent": "pickaxe_head_base",
  "container": {
    "type": "CREATE",
    "id": "this"
  },
  "construct": {
    "type": "PICKAXE_HEAD",
    "target": "CREATE",
    "recipes": [
      {
        "crafting_type": "SCHEMATIC_PART_CRAFTING",
        "ingredients": [
          {
            "id": "this"
          },
          {
            "type": "TOOL_MATERIAL",
            "unique": true,
            "amount": 2
          }
        ]
      }
    ],
    "components": [
      {
        "id": "this"
      },
      {
        "type": "TOOL_MATERIAL",
        "unique": true
      }
    ],
    "slots": [
      {
        "upgrade_type": "SMITHING",
        "category": [
          "OFFENSIVE"
        ],
        "type": "MATERIAL"
      },
      {
        "upgrade_type": "SMITHING",
        "category": [
          "UTILITY"
        ],
        "type": "DYE",
        "tier": 1
      }
    ]
  },
  "properties": {
    "attributes": [
      {
        "id": "schematic-rarity-local",
        "type": "RARITY",
        "order": "BASE",
        "context": "LOCAL",
        "operation": "ADDITION",
        "value": 66
      },
      {
        "id": "schematic-rarity-composite",
        "type": "RARITY",
        "context": "COMPOSITE",
        "operation": "MULTIPLICATION",
        "value": 1.25
      },
      {
        "id": "schematic-durability-composite",
        "type": "DURABILITY",
        "context": "COMPOSITE",
        "operation": "MULTIPLICATION",
        "value": 0.9
      },
      {
        "id": "schematic-attack_damage-composite",
        "type": "ATTACK_DAMAGE",
        "context": "COMPOSITE",
        "operation": "MULTIPLICATION",
        "value": 1.4
      },
      {
        "id": "schematic-weight-composite",
        "type": "WEIGHT",
        "context": "COMPOSITE",
        "operation": "MULTIPLICATION",
        "value": 0.6
      }
    ]
  },
  "custom_data": {
    "ingredient_count": {
      "value": 2,
      "context": "LOCAL"
    }
  }
}
