{
  "schemaVersion": 1,
  "id": "forgero-core",
  "version": "${version}",
  "name": "Forgero core",
  "description": "Equipment crafting expansion mod for Fabric!",
  "authors": [
    "Sigmund Granaas Sandring"
  ],
  "contact": {
    "website": "https://sigmundgranaas.com",
    "repo": "https://github.com/sigmundgranaas/forgero"
  },
  "license": "MIT",
  "icon": "assets/forgero/icon.png",
  "environment": "*",
  "entrypoints": {
  },
  "mixins": [
  ],
  "depends": {
    "fabricloader": ">=0.12.12",
    "fabric": "*",
    "minecraft": "*",
    "java": ">=17"
  },
  "custom": {
  }
}