{
  "type": "SWORD_BLADE",
  "models": [
    {
      "name": "broadsword_blade",
      "template": "broadsword_blade.png",
      "type": "GENERATE",
      "palette": "TOOL_MATERIAL",
      "order": 40
    },
    {
      "name": "sword_blade_material",
      "variants": [
        {
          "target": [
            "model:broadsword_blade.png"
          ],
          "template": "broadsword_blade_tip_reinforcement.png"
        }
      ]
    },
    {
      "target": [
        "type:TOOL_MATERIAL",
        "id:broadsword_blade-schematic"
      ],
      "modelType": "BASED_COMPOSITE",
      "template": "broadsword_blade"
    }
  ]
}