{
  "type": "MAKESHIFT",
  "name": "tnt",
  "parent": "makeshift_base",
  "container": {
    "type": "HOST",
    "id": "minecraft:tnt"
  },
  "properties": {
    "features": [
      {
        "type": "minecraft:on_hit",
        "on_hit": {
          "type": "minecraft:explosion",
          "target": "minecraft:targeted_entity",
          "power": 2
        },
        "after_use": [
          {
            "type": "minecraft:stack_damage",
            "damage":  200
          }
        ],
        "title": "Explodes on impact"
      },
      {
        "type": "minecraft:on_hit_block",
        "on_hit": {
          "type": "minecraft:explosion",
          "power": 2
        },
        "after_use": [
          {
            "type": "minecraft:stack_damage",
            "damage":  200
          }
        ]
      }
    ]
  },
  "palette": {
    "name": "fire_charge"
  }
}
