{
  "type": "HOE_HEAD_SCHEMATIC",
  "name": "mastercrafted_hoe_head-schematic",
  "parent": "tool_part_head_schematic",
  "container": {
    "type": "CREATE",
    "id": "this"
  },
  "construct": {
    "type": "HOE_HEAD",
    "target": "CREATE",
    "recipes": [
      {
        "crafting_type": "SCHEMATIC_PART_CRAFTING",
        "ingredients": [
          {
            "id": "this"
          },
          {
            "type": "TOOL_MATERIAL",
            "unique": true,
            "amount": 2
          }
        ]
      }
    ],
    "components": [
      {
        "id": "this"
      },
      {
        "type": "TOOL_MATERIAL",
        "unique": true
      }
    ],
    "slots": [
      {
        "upgrade_type": "SMITHING",
        "category": [
          "OFFENSIVE"
        ],
        "type": "MATERIAL",
        "tier": 1
      }
    ]
  },
  "properties": {
    "attributes": [
      {
        "type": "RARITY",
        "order": "BASE",
        "operation": "ADDITION",
        "category": "LOCAL",
        "value": 40
      },
      {
        "type": "ATTACK_DAMAGE",
        "order": "COMPOSITE",
        "operation": "MULTIPLICATION",
        "value": 1.8
      },
      {
        "type": "DURABILITY",
        "order": "COMPOSITE",
        "operation": "MULTIPLICATION",
        "value": 1.4
      },
      {
        "type": "MINING_SPEED",
        "order": "COMPOSITE",
        "operation": "ADDITION",
        "value": 1.5
      },
      {
        "type": "ATTACK_SPEED",
        "order": "COMPOSITE",
        "operation": "ADDITION",
        "value": -2.4
      }
    ],
    "active": [
      {
        "type": "BLOCK_BREAKING_PATTERN",
        "pattern": [
          "xxx",
          "xxx",
          "xxx"
        ]
      }
    ]
  },
  "custom_data": {
    "ingredient_count": "2"
  }
}