{
  "parent": "minecraft:recipes/root",
  "criteria": {
    "has_the_recipe": {
      "conditions": {
        "recipe": "forgero:calcite-refined_sword_blade-schematic_recipe"
      },
      "trigger": "minecraft:recipe_unlocked"
    },
    "okay": {
      "conditions": {
        "recipe": "forgero:calcite-refined_sword_blade-schematic_recipe"
      },
      "trigger": "minecraft:recipe_unlocked"
    }
  },
  "requirements": [
    [
      "okay",
      "has_the_recipe"
    ]
  ],
  "rewards": {
    "recipes": [
      "forgero:calcite-refined_sword_blade-schematic_recipe"
    ]
  }
}